{"version":{"patch":0,"major":0,"minor":1},"pathHierarchy":{"tutorialContainer":2,"articlesContainer":12,"modules":[12],"nodes":[{"name":"hungary","symbolID":{"interfaceLanguage":"swift","precise":"s:18MinimalPackageCore7CountryO7hungaryyA2CmF"}},{"name":"czechRepublic","symbolID":{"interfaceLanguage":"swift","precise":"s:18MinimalPackageCore7CountryO13czechRepublicyA2CmF"}},{"name":"MinimalPackageCore"},{"name":"slovakia","symbolID":{"interfaceLanguage":"swift","precise":"s:18MinimalPackageCore7CountryO8slovakiayA2CmF"}},{"name":"poland","symbolID":{"interfaceLanguage":"swift","precise":"s:18MinimalPackageCore7CountryO6polandyA2CmF"}},{"name":"init(rawValue:)","symbolID":{"interfaceLanguage":"swift","precise":"s:18MinimalPackageCore7CountryO8rawValueACSgSS_tcfc"}},{"name":"Country","symbolID":{"interfaceLanguage":"swift","precise":"s:18MinimalPackageCore7CountryO"},"children":[{"kind":"taskGroup","nodeID":7},{"hash":"7xuhi","kind":"enum.case","nodeID":4},{"hash":"8n784","kind":"method","returnTypes":[],"nodeID":8,"parameterTypes":["Hasher"]},{"hash":"9ozjy","kind":"func.op","returnTypes":["Bool"],"nodeID":13,"parameterTypes":["Self","Self"]},{"hash":"3ln8o","kind":"enum.case","nodeID":3},{"hash":"8xmjz","kind":"enum.case","nodeID":0},{"hash":"3ybpg","kind":"init","returnTypes":[""],"nodeID":5,"parameterTypes":["String"]},{"kind":"anchor","nodeID":11},{"hash":"7imv4","kind":"enum.case","nodeID":1},{"hash":"5niv","kind":"property","nodeID":14},{"kind":"taskGroup","nodeID":10}]},{"name":"Equatable-Implementations"},{"name":"hash(into:)","symbolID":{"interfaceLanguage":"swift","precise":"s:SYsSHRzSH8RawValueSYRpzrlE4hash4intoys6HasherVz_tF::SYNTHESIZED::s:18MinimalPackageCore7CountryO"},"disfavored":3},{"name":"tutorials"},{"name":"RawRepresentable-Implementations"},{"name":"Usage-Example"},{"name":"MinimalPackageCore","symbolID":{"interfaceLanguage":"swift","precise":"MinimalPackageCore"},"children":[{"hash":"dwz8","kind":"enum","nodeID":6}]},{"name":"!=(_:_:)","symbolID":{"interfaceLanguage":"swift","precise":"s:SQsE2neoiySbx_xtFZ::SYNTHESIZED::s:18MinimalPackageCore7CountryO"},"disfavored":3},{"name":"hashValue","symbolID":{"interfaceLanguage":"swift","precise":"s:SYsSHRzSH8RawValueSYRpzrlE04hashB0Sivp::SYNTHESIZED::s:18MinimalPackageCore7CountryO"},"disfavored":3}],"tutorialOverviewContainer":9},"bundleID":"MinimalPackageCore","nonSymbolPaths":{"2":"\/tutorials\/MinimalPackageCore","10":"\/documentation\/MinimalPackageCore\/Country\/RawRepresentable-Implementations","11":"\/documentation\/MinimalPackageCore\/Country#Usage-Example","7":"\/documentation\/MinimalPackageCore\/Country\/Equatable-Implementations","9":"\/tutorials"}}