[{"usr":"s:SYsSHRzSH8RawValueSYRpzrlE4hash4intoys6HasherVz_tF::SYNTHESIZED::s:18MinimalPackageCore7CountryO","title":"hash(into:)","language":"swift","referenceURL":"doc:\/\/MinimalPackageCore\/documentation\/MinimalPackageCore\/Country\/hash(into:)","availableLanguages":["swift"],"path":"\/documentation\/minimalpackagecore\/country\/hash(into:)","kind":"org.swift.docc.kind.instanceMethod","fragments":[{"text":"func","kind":"keyword"},{"text":" ","kind":"text"},{"text":"hash","kind":"identifier"},{"text":"(","kind":"text"},{"text":"into","kind":"externalParam"},{"text":" ","kind":"text"},{"text":"hasher","kind":"internalParam"},{"text":": ","kind":"text"},{"text":"inout","kind":"keyword"},{"text":" ","kind":"text"},{"text":"Hasher","kind":"typeIdentifier","preciseIdentifier":"s:s6HasherV"},{"text":")","kind":"text"}]},{"usr":"s:18MinimalPackageCore7CountryO","title":"Country","language":"swift","abstract":[{"type":"text","text":"A collection of supported countries within the MinimalPackage ecosystem."}],"referenceURL":"doc:\/\/MinimalPackageCore\/documentation\/MinimalPackageCore\/Country","availableLanguages":["swift"],"path":"\/documentation\/minimalpackagecore\/country","kind":"org.swift.docc.kind.enumeration","fragments":[{"text":"enum","kind":"keyword"},{"text":" ","kind":"text"},{"text":"Country","kind":"identifier"}]},{"usr":"MinimalPackageCore","title":"MinimalPackageCore","language":"swift","referenceURL":"doc:\/\/MinimalPackageCore\/documentation\/MinimalPackageCore","availableLanguages":["swift"],"path":"\/documentation\/minimalpackagecore","kind":"org.swift.docc.kind.module"},{"usr":"s:18MinimalPackageCore7CountryO6polandyA2CmF","title":"Country.poland","language":"swift","abstract":[{"type":"text","text":"The Poland region."}],"referenceURL":"doc:\/\/MinimalPackageCore\/documentation\/MinimalPackageCore\/Country\/poland","availableLanguages":["swift"],"path":"\/documentation\/minimalpackagecore\/country\/poland","kind":"org.swift.docc.kind.enumerationCase","fragments":[{"text":"case","kind":"keyword"},{"text":" ","kind":"text"},{"text":"poland","kind":"identifier"}]},{"usr":"s:18MinimalPackageCore7CountryO13czechRepublicyA2CmF","title":"Country.czechRepublic","language":"swift","abstract":[{"type":"text","text":"The Czech Republic region."}],"referenceURL":"doc:\/\/MinimalPackageCore\/documentation\/MinimalPackageCore\/Country\/czechRepublic","availableLanguages":["swift"],"path":"\/documentation\/minimalpackagecore\/country\/czechrepublic","kind":"org.swift.docc.kind.enumerationCase","fragments":[{"text":"case","kind":"keyword"},{"text":" ","kind":"text"},{"text":"czechRepublic","kind":"identifier"}]},{"usr":"s:18MinimalPackageCore7CountryO7hungaryyA2CmF","title":"Country.hungary","language":"swift","abstract":[{"type":"text","text":"The Hungary region."}],"referenceURL":"doc:\/\/MinimalPackageCore\/documentation\/MinimalPackageCore\/Country\/hungary","availableLanguages":["swift"],"path":"\/documentation\/minimalpackagecore\/country\/hungary","kind":"org.swift.docc.kind.enumerationCase","fragments":[{"text":"case","kind":"keyword"},{"text":" ","kind":"text"},{"text":"hungary","kind":"identifier"}]},{"usr":"s:SQsE2neoiySbx_xtFZ::SYNTHESIZED::s:18MinimalPackageCore7CountryO","title":"!=(_:_:)","language":"swift","referenceURL":"doc:\/\/MinimalPackageCore\/documentation\/MinimalPackageCore\/Country\/!=(_:_:)","availableLanguages":["swift"],"path":"\/documentation\/minimalpackagecore\/country\/!=(_:_:)","kind":"org.swift.docc.kind.operator","fragments":[{"text":"static","kind":"keyword"},{"text":" ","kind":"text"},{"text":"func","kind":"keyword"},{"text":" ","kind":"text"},{"text":"!=","kind":"identifier"},{"text":" ","kind":"text"},{"text":"(","kind":"text"},{"text":"lhs","kind":"internalParam"},{"text":": ","kind":"text"},{"text":"Self","kind":"typeIdentifier"},{"text":", ","kind":"text"},{"text":"rhs","kind":"internalParam"},{"text":": ","kind":"text"},{"text":"Self","kind":"typeIdentifier"},{"text":") -> ","kind":"text"},{"text":"Bool","kind":"typeIdentifier","preciseIdentifier":"s:Sb"}]},{"title":"RawRepresentable Implementations","language":"swift","path":"\/documentation\/minimalpackagecore\/country\/rawrepresentable-implementations","kind":"org.swift.docc.kind.collectionGroup","availableLanguages":["swift"],"referenceURL":"doc:\/\/MinimalPackageCore\/documentation\/MinimalPackageCore\/Country\/RawRepresentable-Implementations"},{"title":"Equatable Implementations","language":"swift","path":"\/documentation\/minimalpackagecore\/country\/equatable-implementations","kind":"org.swift.docc.kind.collectionGroup","availableLanguages":["swift"],"referenceURL":"doc:\/\/MinimalPackageCore\/documentation\/MinimalPackageCore\/Country\/Equatable-Implementations"},{"usr":"s:18MinimalPackageCore7CountryO8rawValueACSgSS_tcfc","title":"init(rawValue:)","language":"swift","referenceURL":"doc:\/\/MinimalPackageCore\/documentation\/MinimalPackageCore\/Country\/init(rawValue:)","availableLanguages":["swift"],"path":"\/documentation\/minimalpackagecore\/country\/init(rawvalue:)","kind":"org.swift.docc.kind.initializer","fragments":[{"text":"init","kind":"keyword"},{"text":"?(","kind":"text"},{"text":"rawValue","kind":"externalParam"},{"text":": ","kind":"text"},{"text":"String","kind":"typeIdentifier","preciseIdentifier":"s:SS"},{"text":")","kind":"text"}]},{"usr":"s:18MinimalPackageCore7CountryO8slovakiayA2CmF","title":"Country.slovakia","language":"swift","abstract":[{"type":"text","text":"The Slovakia region."}],"referenceURL":"doc:\/\/MinimalPackageCore\/documentation\/MinimalPackageCore\/Country\/slovakia","availableLanguages":["swift"],"path":"\/documentation\/minimalpackagecore\/country\/slovakia","kind":"org.swift.docc.kind.enumerationCase","fragments":[{"text":"case","kind":"keyword"},{"text":" ","kind":"text"},{"text":"slovakia","kind":"identifier"}]},{"usr":"s:SYsSHRzSH8RawValueSYRpzrlE04hashB0Sivp::SYNTHESIZED::s:18MinimalPackageCore7CountryO","title":"hashValue","language":"swift","referenceURL":"doc:\/\/MinimalPackageCore\/documentation\/MinimalPackageCore\/Country\/hashValue","availableLanguages":["swift"],"path":"\/documentation\/minimalpackagecore\/country\/hashvalue","kind":"org.swift.docc.kind.instanceProperty","fragments":[{"text":"var","kind":"keyword"},{"text":" ","kind":"text"},{"text":"hashValue","kind":"identifier"},{"text":": ","kind":"text"},{"text":"Int","kind":"typeIdentifier","preciseIdentifier":"s:Si"},{"text":" { ","kind":"text"},{"text":"get","kind":"keyword"},{"text":" }","kind":"text"}]}]